odoo8_addon_stock_ownership_availability_rules-8.0.0.2.0.99.dev32-py3.8-nspkg.pth
odoo_addons/stock_ownership_availability_rules/README.rst
odoo_addons/stock_ownership_availability_rules/__init__.py
odoo_addons/stock_ownership_availability_rules/__openerp__.py
odoo_addons/stock_ownership_availability_rules/i18n/ca.po
odoo_addons/stock_ownership_availability_rules/i18n/de.po
odoo_addons/stock_ownership_availability_rules/i18n/es.po
odoo_addons/stock_ownership_availability_rules/i18n/es_MX.po
odoo_addons/stock_ownership_availability_rules/i18n/fi.po
odoo_addons/stock_ownership_availability_rules/i18n/fr.po
odoo_addons/stock_ownership_availability_rules/i18n/fr_CH.po
odoo_addons/stock_ownership_availability_rules/i18n/hr.po
odoo_addons/stock_ownership_availability_rules/i18n/hr_HR.po
odoo_addons/stock_ownership_availability_rules/i18n/it.po
odoo_addons/stock_ownership_availability_rules/i18n/pt_BR.po
odoo_addons/stock_ownership_availability_rules/i18n/ro.po
odoo_addons/stock_ownership_availability_rules/i18n/sl.po
odoo_addons/stock_ownership_availability_rules/i18n/stock_ownership_availability_rules.pot
odoo_addons/stock_ownership_availability_rules/i18n/tr.po
odoo_addons/stock_ownership_availability_rules/i18n/tr_TR.po
odoo_addons/stock_ownership_availability_rules/i18n/vi_VN.po
odoo_addons/stock_ownership_availability_rules/i18n/zh_CN.po
odoo_addons/stock_ownership_availability_rules/model/__init__.py
odoo_addons/stock_ownership_availability_rules/model/product.py
odoo_addons/stock_ownership_availability_rules/model/quant.py
odoo_addons/stock_ownership_availability_rules/model/stock_change_product_qty.py
odoo_addons/stock_ownership_availability_rules/security/group.xml
odoo_addons/stock_ownership_availability_rules/static/description/icon.png
odoo_addons/stock_ownership_availability_rules/tests/__init__.py
odoo_addons/stock_ownership_availability_rules/tests/test_change_product.py
odoo_addons/stock_ownership_availability_rules/tests/test_default_quant_owner.py
odoo8_addon_stock_ownership_availability_rules-8.0.0.2.0.99.dev32.dist-info/METADATA
odoo8_addon_stock_ownership_availability_rules-8.0.0.2.0.99.dev32.dist-info/WHEEL
odoo8_addon_stock_ownership_availability_rules-8.0.0.2.0.99.dev32.dist-info/namespace_packages.txt
odoo8_addon_stock_ownership_availability_rules-8.0.0.2.0.99.dev32.dist-info/top_level.txt
odoo8_addon_stock_ownership_availability_rules-8.0.0.2.0.99.dev32.dist-info/RECORD
